byted_overpass_douyin_creator_inspiration/__init__.py
byted_overpass_douyin_creator_inspiration-0.0.1.dist-info/METADATA
byted_overpass_douyin_creator_inspiration-0.0.1.dist-info/WHEEL
byted_overpass_douyin_creator_inspiration-0.0.1.dist-info/top_level.txt
byted_overpass_douyin_creator_inspiration-0.0.1.dist-info/RECORD
